vdc/__init__.py
vdc/cleanser.py
vdc/prompts.py
vdc-1.0.1.dist-info/LICENSE
vdc-1.0.1.dist-info/METADATA
vdc-1.0.1.dist-info/WHEEL
vdc-1.0.1.dist-info/top_level.txt
vdc-1.0.1.dist-info/RECORD
