Metadata-Version: 2.2
Name: vdc
Version: 1.0.1
Summary: A Python package for verifying consistency between multimodal data
Home-page: https://github.com/zihao-ai/vdc
Author: Zihao Zhu
Author-email: zihaozhu1996@gmail.com
License: MIT
Project-URL: Bug Tracker, https://github.com/zihao-ai/vdc/issues
Classifier: Programming Language :: Python :: 3
Classifier: License :: OSI Approved :: MIT License
Classifier: Operating System :: OS Independent
Requires-Python: >=3.10
License-File: LICENSE
Requires-Dist: openai>=1.12.0
Requires-Dist: requests>=2.24.0
Requires-Dist: pandas>=1.0.0
